[
  {
    "id": 1,
    "name": "Projet 1",
    "type":{
      "UI":true,
      "coding":false,
      "motion":true
    },
    "thumbs": "ET_UI_Thumbs.png",
    "link": "https://www.behance.net/gallery/157557751/DATA-WEBSITE-Territorial-inequality-in-Lyon",
    "author":"@knch"
  },
  {
    "id": 2,
    "name": "Projet 2",
    "type":{
      "UI":true,
      "coding":true,
      "motion":true
    },
    "thumbs":"ET_UI_Thumbs.png",
    "link": "https://www.behance.net/gallery/157557751/DATA-WEBSITE-Territorial-inequality-in-Lyon",
    "author":"@knch"
  },

  {
    "id": 3,
    "name": "Projet 3",
    "type":{
      "UI":false,
      "coding":false,
      "motion":true
    },
    "thumbs": "ET_UI_Thumbs.png",
    "link": "https://www.behance.net/gallery/157557751/DATA-WEBSITE-Territorial-inequality-in-Lyon",
    "author":"@knch"
  },

  {
    "id": 4,
    "name": "Projet 4",
    "type":{
      "UI":true,
      "coding":true,
      "motion":false
    },
    "thumbs": "ET_UI_Thumbs.png",
    "link": "https://www.behance.net/gallery/157557751/DATA-WEBSITE-Territorial-inequality-in-Lyon",
    "author":"@knch"
  },

  {
    "id": 5,
    "name": "Projet 3",
    "type":{
      "UI":false,
      "coding":false,
      "motion":true
    },
    "thumbs": "ET_UI_Thumbs.png",
    "link": "https://www.behance.net/gallery/157557751/DATA-WEBSITE-Territorial-inequality-in-Lyon",
    "author":"@knch"
  },


  {
    "id": 3,
    "name": "Projet 3",
    "type":{
      "UI":false,
      "coding":false,
      "motion":true
    },
    "thumbs": "ET_UI_Thumbs.png",
    "link": "https://www.behance.net/gallery/157557751/DATA-WEBSITE-Territorial-inequality-in-Lyon",
    "author":"@knch"
  },


  {
    "id": 3,
    "name": "Projet 3",
    "type":{
      "UI":false,
      "coding":false,
      "motion":true
    },
    "thumbs": "ET_UI_Thumbs.png",
    "link": "https://www.behance.net/gallery/157557751/DATA-WEBSITE-Territorial-inequality-in-Lyon",
    "author":"@knch"
  },
  {
    "id": 3,
    "name": "Projet 3",
    "type":{
      "UI":false,
      "coding":false,
      "motion":true
    },
    "thumbs": "ET_UI_Thumbs.png",
    "link": "https://www.behance.net/gallery/157557751/DATA-WEBSITE-Territorial-inequality-in-Lyon",
    "author":"@knch"
  },
  {
    "id": 3,
    "name": "Projet 3",
    "type":{
      "UI":false,
      "coding":false,
      "motion":true
    },
    "thumbs": "ET_UI_Thumbs.png",
    "link": "https://www.behance.net/gallery/157557751/DATA-WEBSITE-Territorial-inequality-in-Lyon",
    "author":"@knch"
  }

]
